{"QkNeqTgMRu/I8qTtie3ZJA==":"fwl%20logo-122x94.png","GcbTv3x/CFCfpEjS3AEx0g==":"fwl%20logo-122x94.png","zAtxrTkYx8ckCbP41qLdBg==":"mbr-1281x1920.jpg","bBTNz6pdIgPru4H+tybtIA==":"mbr-1-1281x1920.jpg","2DICkvEDotSrjFS4LCWu6A==":"fwl%20logo-122x94.png","L6GwmgCwxEB20fx9S3XDWw==":"fwl%20logo-220x169.png","nZZfTz3UEKB/J4qqAhFa0w==":"fwl%20logo-192x147.png","Evut7wZJ53EZGukfOmMCpQ==":"mbr-1920x1440.jpg","p9nOC1/dlQUFBQ4qZWMo2g==":"impossible-possible-1280x944.jpg","Gp/2AUczanemtJtBHsZ9cw==":"impossible-possible-1-1280x944.jpg","NPCTWpypqgDJtuIYouoC+A==":"face1.jpg","M685RuVb/HThixtneI5Piw==":"face3.jpg","qqzGUXDYkUqu9m7laZ83Rw==":"face2.jpg","0OOE1Usrtktm437Z/qTMRQ==":"background2.jpg","ihlkf69UyfSmhSyJ1Jvc6w==":"jumbotron.jpg"}